nonebot_plugin_updater/__init__.py
nonebot_plugin_updater/commands.py
nonebot_plugin_updater/config.py
nonebot_plugin_updater/templates/check_plugin_update.jinja2
nonebot_plugin_updater/templates/plugin_info.jinja2
nonebot_plugin_updater/utils/addition_for_htmlrender.py
nonebot_plugin_updater/utils/common.py
nonebot_plugin_updater/utils/models.py
nonebot_plugin_updater/utils/updater.py
nonebot_plugin_updater-0.2.5.dist-info/METADATA
nonebot_plugin_updater-0.2.5.dist-info/WHEEL
nonebot_plugin_updater-0.2.5.dist-info/licenses/LICENSE
nonebot_plugin_updater-0.2.5.dist-info/RECORD
