Metadata-Version: 2.4
Name: nonebot-plugin-updater
Version: 0.2.5
Summary: 一款全新的检测已安装插件更新情况的插件
Author-email: hanasa2023 <hanasakayui2022@gmail.com>
License: MIT
License-File: LICENSE
Requires-Python: <4.0,>=3.9
Requires-Dist: httpx>=0.27.2
Requires-Dist: nonebot-plugin-alconna>=0.53.0
Requires-Dist: nonebot-plugin-htmlrender>=0.3.5
Requires-Dist: nonebot2>=2.3.3
Requires-Dist: packaging>=25.0
Requires-Dist: toml>=0.10.2
Requires-Dist: tomli>=2.0.1; python_version < '3.11'
